{
  "gitSyncId": "678e072094bc2e43fa935346_0b3e91c3-f514-41fb-abc9-72480b6958e3",
  "id": "Customers_utils.addCustomer",
  "pluginId": "js-plugin",
  "pluginType": "JS",
  "unpublishedAction": {
    "actionConfiguration": {
      "encodeParamsToggle": true,
      "isAsync": true,
      "jsArguments": [],
      "paginationType": "NONE",
      "timeoutInMillisecond": 10000
    },
    "collectionId": "Customers_utils",
    "confirmBeforeExecute": false,
    "datasource": {
      "isAutoGenerated": false,
      "name": "UNUSED_DATASOURCE",
      "pluginId": "js-plugin"
    },
    "dynamicBindingPathList": [
      {
        "key": "body"
      }
    ],
    "executeOnLoad": false,
    "fullyQualifiedName": "utils.addCustomer",
    "name": "addCustomer",
    "pageId": "Customers",
    "userSetOnLoad": false
  }
}